octanedb/__init__.py
octanedb/_version.py
octanedb/cli.py
octanedb/collection.py
octanedb/core.py
octanedb/embeddings.py
octanedb/index.py
octanedb/query.py
octanedb/storage.py
octanedb/utils.py
octanedb-1.0.1.dist-info/licenses/LICENSE
octanedb-1.0.1.dist-info/METADATA
octanedb-1.0.1.dist-info/WHEEL
octanedb-1.0.1.dist-info/entry_points.txt
octanedb-1.0.1.dist-info/top_level.txt
octanedb-1.0.1.dist-info/RECORD
