Metadata-Version: 2.4
Name: octanedb
Version: 1.0.1
Summary: A lightweight, high-performance Python vector database library with ChromaDB compatibility
Home-page: https://github.com/RijinRaju/octanedb
Author: Rijin
Author-email: Rijin <rijinraj856@gmail.com>
Maintainer-email: Rijin <rijinraj856@gmail.com>
License: MIT
Project-URL: Homepage, https://github.com/RijinRaju/octanedb
Project-URL: Documentation, https://github.com/RijinRaju/octanedb#readme
Project-URL: Repository, https://github.com/RijinRaju/octanedb
Project-URL: Bug Tracker, https://github.com/RijinRaju/octanedb/issues
Project-URL: Source Code, https://github.com/RijinRaju/octanedb
Project-URL: Changelog, https://github.com/RijinRaju/octanedb/blob/main/CHANGELOG.md
Keywords: vector-database,vector-search,embeddings,similarity-search,machine-learning,ai,chromadb-compatible,hnsw,fast,lightweight
Platform: any
Classifier: Development Status :: 5 - Production/Stable
Classifier: Intended Audience :: Developers
Classifier: Intended Audience :: Science/Research
Classifier: License :: OSI Approved :: MIT License
Classifier: Operating System :: OS Independent
Classifier: Programming Language :: Python :: 3
Classifier: Programming Language :: Python :: 3.8
Classifier: Programming Language :: Python :: 3.9
Classifier: Programming Language :: Python :: 3.10
Classifier: Programming Language :: Python :: 3.11
Classifier: Programming Language :: Python :: 3.12
Classifier: Topic :: Database
Classifier: Topic :: Scientific/Engineering :: Artificial Intelligence
Classifier: Topic :: Software Development :: Libraries :: Python Modules
Classifier: Topic :: Text Processing :: Linguistic
Requires-Python: >=3.8
License-File: LICENSE
Requires-Dist: numpy>=1.21.0
Requires-Dist: h5py>=3.7.0
Requires-Dist: msgpack>=1.0.0
Requires-Dist: tqdm>=4.62.0
Requires-Dist: sentence-transformers>=2.2.0
Requires-Dist: transformers>=4.20.0
Requires-Dist: torch>=1.12.0
Provides-Extra: dev
Requires-Dist: pytest>=7.0.0; extra == "dev"
Requires-Dist: pytest-cov>=4.0.0; extra == "dev"
Requires-Dist: black>=22.0.0; extra == "dev"
Requires-Dist: isort>=5.10.0; extra == "dev"
Requires-Dist: flake8>=5.0.0; extra == "dev"
Requires-Dist: mypy>=1.0.0; extra == "dev"
Provides-Extra: docs
Requires-Dist: sphinx>=5.0.0; extra == "docs"
Requires-Dist: sphinx-rtd-theme>=1.0.0; extra == "docs"
Requires-Dist: myst-parser>=0.18.0; extra == "docs"
Provides-Extra: benchmark
Requires-Dist: matplotlib>=3.5.0; extra == "benchmark"
Requires-Dist: pandas>=1.4.0; extra == "benchmark"
Requires-Dist: seaborn>=0.11.0; extra == "benchmark"
Provides-Extra: all
Requires-Dist: octanedb[benchmark,dev,docs]; extra == "all"
Dynamic: license-file
